VideoTracking/VideoTracking.py
VideoTracking/VideoTrackingWindow.py
VideoTracking/VideoTracking_old.py
VideoTracking/VideoTraking_video.py
VideoTracking/__init__.py
VideoTracking/cvtracker.py
VideoTracking/labelImg.py
VideoTracking/motpy.py
VideoTracking/test2.py
VideoTracking/test_QRunnable.py
VideoTracking/test_vlc.py
libs/__init__.py
libs/canvas.py
libs/colorDialog.py
libs/constants.py
libs/hashableQListWidgetItem.py
libs/labelDialog.py
libs/labelFile.py
libs/lib.py
libs/pascal_voc_io.py
libs/settings.py
libs/shape.py
libs/stringBundle.py
libs/toolBar.py
libs/ustr.py
libs/utils.py
libs/yolo_io.py
libs/zoomWidget.py
src/QVideoWidgetRect.py
src/TrackingWindow.py
src/VideoTrackingWindow.py
src/__init__.py
src/ui_mainwindow.py
src/libs_old/__init__.py
src/libs_old/canvas.py
src/libs_old/category.py
src/libs_old/constants.py
src/libs_old/hashableQListWidgetItem.py
src/libs_old/labelDialog.py
src/libs_old/shape.py
src/libs_old/ustr.py
src/libs_old/utils.py
VideoTracking-0.0.16.dist-info/METADATA
VideoTracking-0.0.16.dist-info/WHEEL
VideoTracking-0.0.16.dist-info/entry_points.txt
VideoTracking-0.0.16.dist-info/top_level.txt
VideoTracking-0.0.16.dist-info/RECORD
