Metadata-Version: 2.1
Name: VideoTracking
Version: 0.0.16
Summary: Video Tracking Annotation Tool
Home-page: https://github.com/silviogiancola/VideoTracking/
Author: Silvio Giancola
Author-email: silvio.giancola@kaust.edu.sa
License: MIT license
Keywords: TCPClient
Platform: UNKNOWN
Classifier: Development Status :: 5 - Production/Stable
Classifier: Intended Audience :: Developers
Classifier: License :: OSI Approved :: MIT License
Classifier: Natural Language :: English
Classifier: Programming Language :: Python :: 3
Classifier: Programming Language :: Python :: 3.3
Classifier: Programming Language :: Python :: 3.4
Classifier: Programming Language :: Python :: 3.5
Classifier: Programming Language :: Python :: 3.6
Classifier: Programming Language :: Python :: 3.7
Requires-Python: >=3.0.0
Requires-Dist: pyqt5
Requires-Dist: numpy
Requires-Dist: opencv-contrib-python (==3.4.5.20)
Requires-Dist: scikit-video
